{
  "job_id": "4384810054",
  "company": "Bionorica SE",
  "title": "Marketing Analyst / Sales Analyst (m/w/d)",
  "url": "https://www.linkedin.com/jobs/view/4384810054/",
  "posted_date": "",
  "match_score": 72.0,
  "required_skills": [
    "Business administration degree (Betriebswirtschaftliche Ausbildung)",
    "Strong analytical skills and numerical understanding",
    "Strategic-conceptual thinking",
    "MS Office (Excel, PowerPoint) — advanced",
    "SAP knowledge"
  ],
  "bonus_skills": [
    "Good English skills",
    "Team-oriented working style",
    "Project management"
  ],
  "matched_skills": [
    "Business/management degrees (3 degrees incl. Master of Management)",
    "Strong analytical skills — core throughout all roles",
    "Excel and PowerPoint — explicitly mentioned across CV",
    "Strategic-conceptual thinking (market segmentation, GTM strategy)",
    "English C1",
    "Project coordination (Hapag-Lloyd, HSBC)"
  ],
  "missing_skills": [
    "SAP (not mentioned in CV tools)",
    "Pharmaceutical / healthcare industry knowledge",
    "Sales analytics experience"
  ],
  "core_responsibilities": [
    "Market analysis, market data, product analysis and reporting for Marketing & Sales leadership",
    "Strategic annual and budget planning support",
    "Coordination of central marketing/sales projects (e.g. marketing plan, bonus calculation)",
    "Interface function for cost planning, investment management, forecast and price management",
    "Accompanying global projects at national level"
  ],
  "culture_keywords": [
    "Familienunternehmen", "soziale Verantwortung", "Phytoneering", "Wachstum", "Flexibilität"
  ],
  "recommended_emphasis": [
    "Lead with analytical reporting and market analysis experience across multiple industries",
    "Highlight Excel and PowerPoint as primary tools explicitly",
    "Frame HSBC budget planning work as financial planning and cost monitoring analogue",
    "Frame GRG Banking market analysis as product/market analysis experience",
    "Note SAP gap honestly — consider omitting if not central to role"
  ],
  "company_info": {
    "size": "1,001-5,000",
    "size_source": "jd_text",
    "size_raw": "ca. 2200 Mitarbeiter weltweit"
  }
}
